mesh_account_v1/__init__.py
mesh_account_v1/v1_pb.py
mesh_account_v1-0.1.0.dist-info/licenses/LICENSE
mesh_account_v1-0.1.0.dist-info/METADATA
mesh_account_v1-0.1.0.dist-info/WHEEL
mesh_account_v1-0.1.0.dist-info/top_level.txt
mesh_account_v1-0.1.0.dist-info/RECORD
